etc/ansible/roles/network-runner/README.md
etc/ansible/roles/network-runner/defaults/main.yml
etc/ansible/roles/network-runner/handlers/main.yml
etc/ansible/roles/network-runner/meta/main.yml
etc/ansible/roles/network-runner/providers/cumulus/add_trunk_vlan.yaml
etc/ansible/roles/network-runner/providers/cumulus/conf_access_port.yaml
etc/ansible/roles/network-runner/providers/cumulus/conf_trunk_port.yaml
etc/ansible/roles/network-runner/providers/cumulus/create_vlan.yaml
etc/ansible/roles/network-runner/providers/cumulus/defaults.yaml
etc/ansible/roles/network-runner/providers/cumulus/delete_port.yaml
etc/ansible/roles/network-runner/providers/cumulus/delete_trunk_vlan.yaml
etc/ansible/roles/network-runner/providers/cumulus/delete_vlan.yaml
etc/ansible/roles/network-runner/providers/cumulus/list_vlans.yaml
etc/ansible/roles/network-runner/providers/dellemc.os9.os9/add_trunk_vlan.yaml
etc/ansible/roles/network-runner/providers/dellemc.os9.os9/conf_access_port.yaml
etc/ansible/roles/network-runner/providers/dellemc.os9.os9/conf_trunk_port.yaml
etc/ansible/roles/network-runner/providers/dellemc.os9.os9/create_vlan.yaml
etc/ansible/roles/network-runner/providers/dellemc.os9.os9/defaults.yaml
etc/ansible/roles/network-runner/providers/dellemc.os9.os9/delete_port.yaml
etc/ansible/roles/network-runner/providers/dellemc.os9.os9/delete_trunk_vlan.yaml
etc/ansible/roles/network-runner/providers/dellemc.os9.os9/delete_vlan.yaml
etc/ansible/roles/network-runner/providers/dellemc.os9.os9/list_vlans.yaml
etc/ansible/roles/network-runner/providers/dellos10/add_trunk_vlan.yaml
etc/ansible/roles/network-runner/providers/dellos10/conf_access_port.yaml
etc/ansible/roles/network-runner/providers/dellos10/conf_trunk_port.yaml
etc/ansible/roles/network-runner/providers/dellos10/create_vlan.yaml
etc/ansible/roles/network-runner/providers/dellos10/defaults.yaml
etc/ansible/roles/network-runner/providers/dellos10/delete_port.yaml
network_runner-0.3.6.dist-info/LICENSE
network_runner-0.3.6.dist-info/METADATA
network_runner-0.3.6.dist-info/WHEEL
network_runner-0.3.6.dist-info/pbr.json
network_runner-0.3.6.dist-info/top_level.txt
network_runner-0.3.6.dist-info/RECORD
